aero_astro_calc/PlaneStress.py
aero_astro_calc/__init__.py
aero_astro_calc/dependencies/LatexLabel.py
aero_astro_calc/dependencies/__init__.py
aero_astro_calc-2020.2.0.dist-info/LICENSE
aero_astro_calc-2020.2.0.dist-info/METADATA
aero_astro_calc-2020.2.0.dist-info/WHEEL
aero_astro_calc-2020.2.0.dist-info/top_level.txt
aero_astro_calc-2020.2.0.dist-info/RECORD
